setup.py
distributions9989/Binomialdistribution.py
distributions9989/Gaussiandistribution.py
distributions9989/Generaldistribution.py
distributions9989/__init__.py
distributions9989.egg-info/PKG-INFO
distributions9989.egg-info/SOURCES.txt
distributions9989.egg-info/dependency_links.txt
distributions9989.egg-info/not-zip-safe
distributions9989.egg-info/top_level.txt